pegghy_viewer/app.py
pegghy_viewer/py.typed
pegghy_viewer-1.0.2.dist-info/licenses/LICENSE
pegghy_viewer-1.0.2.dist-info/METADATA
pegghy_viewer-1.0.2.dist-info/WHEEL
pegghy_viewer-1.0.2.dist-info/entry_points.txt
pegghy_viewer-1.0.2.dist-info/top_level.txt
pegghy_viewer-1.0.2.dist-info/RECORD
