Metadata-Version: 2.4
Name: PEGGHy-Viewer
Version: 1.0.2
Summary: PEGGHy-Viewer is the viewer microservice of PEGGHy
Author-email: Geode-solutions <team-web@geode-solutions.com>
Project-URL: Homepage, https://github.com/Geode-solutions/PEGGHy-Viewer
Project-URL: Bug Tracker, https://github.com/Geode-solutions/PEGGHy-Viewer/issues
Classifier: Programming Language :: Python :: 3
Classifier: License :: OSI Approved :: MIT License
Classifier: Operating System :: OS Independent
Requires-Python: <3.13,>=3.9
License-File: LICENSE
Requires-Dist: opengeodeweb-viewer==1.*,>=1.13.4
Dynamic: license-file
